[
    {
        "id": "1",
        "name": "Arcane élémentaire",
        "slug": "elements",
        "deleted": "0"
    },
    {
        "id": "2",
        "name": "Arcane cinétique",
        "slug": "kinetic",
        "deleted": "0"
    },
    {
        "id": "3",
        "name": "Arcane de la vie",
        "slug": "life",
        "deleted": "0"
    },
    {
        "id": "4",
        "name": "Arcane de la mort",
        "slug": "death",
        "deleted": "0"
    },
    {
        "id": "5",
        "name": "Arcane de l'espace-temps",
        "slug": "space-time",
        "deleted": "0"
    },
    {
        "id": "6",
        "name": "Arcane de l'intellect",
        "slug": "intellect",
        "deleted": "0"
    },
    {
        "id": "7",
        "name": "Arcane éthéré",
        "slug": "ether",
        "deleted": "0"
    },
    {
        "id": "8",
        "name": "Arcane coercitif",
        "slug": "coercive",
        "deleted": "0"
    }
]